PCA9685_PicoPlanetDev/PCA9685.py
PCA9685_PicoPlanetDev/__init__.py
pca9685_picoplanetdev-0.0.5.dist-info/METADATA
pca9685_picoplanetdev-0.0.5.dist-info/WHEEL
pca9685_picoplanetdev-0.0.5.dist-info/licenses/LICENSE
pca9685_picoplanetdev-0.0.5.dist-info/RECORD
